corrupter/__init__.py
corrupter/main.py
corrupter-1.1.0.dist-info/licenses/LICENSE
corrupter-1.1.0.dist-info/METADATA
corrupter-1.1.0.dist-info/WHEEL
corrupter-1.1.0.dist-info/entry_points.txt
corrupter-1.1.0.dist-info/top_level.txt
corrupter-1.1.0.dist-info/RECORD
