Metadata-Version: 2.4
Name: corrupter
Version: 1.1.0
Summary: 一个简洁而强大的文件损坏模拟器。
Author-email: miaonya <star2022520@outlook.com>
License: Copyright 2025 miaonya
Project-URL: Homepage, https://github.com/miaonya520/Corrupter
Keywords: corrupt,file,glitch,testing,simulation,binary
Classifier: Development Status :: 5 - Production/Stable
Classifier: Environment :: Console
Classifier: Intended Audience :: Developers
Classifier: Intended Audience :: System Administrators
Classifier: License :: OSI Approved :: MIT License
Classifier: Operating System :: OS Independent
Classifier: Programming Language :: Python :: 3
Classifier: Programming Language :: Python :: 3.6
Classifier: Programming Language :: Python :: 3.7
Classifier: Programming Language :: Python :: 3.8
Classifier: Programming Language :: Python :: 3.9
Classifier: Programming Language :: Python :: 3.10
Classifier: Programming Language :: Python :: 3.11
Classifier: Topic :: Security
Classifier: Topic :: Software Development :: Testing
Classifier: Topic :: Utilities
Requires-Python: >=3.6
License-File: LICENSE
Dynamic: license-file
